Metadata-Version: 2.1
Name: ezneural
Version: 0.2
Summary: простая библеотека которая позволит вам создать нейросеть в 1 строку кода (made by Kim)
Home-page: UNKNOWN
Author-email: kimka230510@gmail.com
License: UNKNOWN
Platform: UNKNOWN
